{
    "t0x7dyqmsuhvv": {
        "now_playing": "https://www.radiojar.com/api/stations/t0x7dyqmsuhvv/now_playing/",
        "stream": "http://n06.radiojar.com/t0x7dyqmsuhvv?rj-ttl=5&rj-tok=AAABmFLMuXQAgKUDbnqGmvn8sg",
        "name": "99 FM Ράδιο 1"
    },
    "h693vkmhe5uvv": {
        "now_playing": "https://www.radiojar.com/api/stations/h693vkmhe5uvv/now_playing/",
        "stream": "https://stream.radiojar.com/h693vkmhe5uvv",
        "name": "Alepou Radio"
    },
    "xcdg6yggzfeuv": {
        "now_playing": "https://www.radiojar.com/api/stations/xcdg6yggzfeuv/now_playing/",
        "stream": "https://stream.radiojar.com/xcdg6yggzfeuv",
        "name": "Alpha Radio 98.9"
    },
    "wxc5sezupy5tv": {
        "now_playing": "https://www.radiojar.com/api/stations/wxc5sezupy5tv/now_playing/",
        "stream": "http://n0a.radiojar.com/wxc5sezupy5tv?rj-ttl=5&rj-tok=AAABmFLNNdQAfc7NeuP2irGriQ",
        "name": "Alpha Καστοριά"
    },
    "g34k4f92n74tv": {
        "now_playing": "https://www.radiojar.com/api/stations/g34k4f92n74tv/now_playing/",
        "stream": "https://stream.radiojar.com/g34k4f92n74tv",
        "name": "Arcadia Τρίπολη"
    },
    "e206r95qsp8uv": {
        "now_playing": "https://www.radiojar.com/api/stations/e206r95qsp8uv/now_playing/",
        "stream": "http://n03.radiojar.com/e206r95qsp8uv?rj-ttl=5&rj-tok=AAABmFLNe90AzTjeuHTgRbZaiA",
        "name": "Athens Free Radio"
    },
    "9ndpdg3c0s8uv": {
        "now_playing": "https://www.radiojar.com/api/stations/9ndpdg3c0s8uv/now_playing/",
        "stream": "https://stream.radiojar.com/9ndpdg3c0s8uv",
        "name": "Athens Up Radio"
    },
    "3h7ncy1y9vzuv": {
        "now_playing": "https://www.radiojar.com/api/stations/3h7ncy1y9vzuv/now_playing/",
        "stream": "https://stream.radiojar.com/3h7ncy1y9vzuv",
        "name": "Bobos Family"
    },
    "252ry9dgytzuv": {
        "now_playing": "https://www.radiojar.com/api/stations/252ry9dgytzuv/now_playing/",
        "stream": "https://stream.radiojar.com/252ry9dgytzuv",
        "name": "Camara Radio"
    },
    "n4dzb3znn3quv": {
        "now_playing": "https://www.radiojar.com/api/stations/n4dzb3znn3quv/now_playing/",
        "stream": "https://stream.radiojar.com/n4dzb3znn3quv",
        "name": "Chillout Tree Pines"
    },
    "duh3nm1v6hhvv": {
        "now_playing": "https://www.radiojar.com/api/stations/duh3nm1v6hhvv/now_playing/",
        "stream": "http://n01.radiojar.com/duh3nm1v6hhvv?rj-ttl=5&rj-tok=AAABmFLOKLIAC08jpMFEkOwsgQ",
        "name": "Cosmos 103.8"
    },
    "htczr9epmchvv": {
        "now_playing": "https://www.radiojar.com/api/stations/htczr9epmchvv/now_playing/",
        "stream": "https://stream.radiojar.com/htczr9epmchvv",
        "name": "Crystal"
    },
    "uf6x8w5f81ac": {
        "now_playing": "https://www.radiojar.com/api/stations/uf6x8w5f81ac/now_playing/",
        "stream": "https://stream.radiojar.com/uf6x8w5f81ac",
        "name": "DemoJar"
    },
    "opa-radio": {
        "now_playing": "https://www.radiojar.com/api/stations/opa-radio/now_playing/",
        "stream": "http://n0e.radiojar.com/opa-radio?rj-ttl=5&rj-tok=AAABmFLOfsEAM5wL6Nk8UHBjFQ",
        "name": "Music Ward"
    },
    "cthtwxk5yvduv": {
        "now_playing": "https://www.radiojar.com/api/stations/cthtwxk5yvduv/now_playing/",
        "stream": "https://stream.radiojar.com/cthtwxk5yvduv",
        "name": "Easy FM 972"
    },
    "su1eg54afzwtv": {
        "now_playing": "https://www.radiojar.com/api/stations/su1eg54afzwtv/now_playing/",
        "stream": "https://stream.radiojar.com/su1eg54afzwtv",
        "name": "Eternal"
    },
    "072mdmpbfq8uv": {
        "now_playing": "https://www.radiojar.com/api/stations/072mdmpbfq8uv/now_playing/",
        "stream": "https://stream.radiojar.com/072mdmpbfq8uv",
        "name": "Fade Radio"
    },
    "garavelas-radio-gr": {
        "now_playing": "https://www.radiojar.com/api/stations/garavelas-radio-gr/now_playing/",
        "stream": "https://stream.radiojar.com/garavelas-radio-gr",
        "name": "Garavelas"
    },
    "8tqwqkrhk48uv": {
        "now_playing": "https://www.radiojar.com/api/stations/8tqwqkrhk48uv/now_playing/",
        "stream": "https://stream.radiojar.com/8tqwqkrhk48uv",
        "name": "Jazz Breeze"
    },
    "gphtvb4env5tv": {
        "now_playing": "https://www.radiojar.com/api/stations/gphtvb4env5tv/now_playing/",
        "stream": "https://stream.radiojar.com/gphtvb4env5tv",
        "name": "Legend FM 88.6"
    },
    "gt0xy4z88f0uv": {
        "now_playing": "https://www.radiojar.com/api/stations/gt0xy4z88f0uv/now_playing/",
        "stream": "http://n03.radiojar.com/gt0xy4z88f0uv?rj-ttl=5&rj-tok=AAABmFLO-UwADjc0ReBn2JVy6w",
        "name": "Love 97.5 Classics"
    },
    "tkeve70hqd0uv": {
        "now_playing": "https://www.radiojar.com/api/stations/tkeve70hqd0uv/now_playing/",
        "stream": "http://n10.radiojar.com/tkeve70hqd0uv?rj-ttl=5&rj-tok=AAABmFLPS9YAJP--yTarN3O0Nw",
        "name": "Love 97.5 Trap"
    },
    "20n2b23u7mruv": {
        "now_playing": "https://www.radiojar.com/api/stations/20n2b23u7mruv/now_playing/",
        "stream": "http://n01.radiojar.com/20n2b23u7mruv?rj-ttl=5&rj-tok=AAABmFLPgWIAj22BGb9xrg7w-w",
        "name": "Love 97.5 Z"
    },
    "qt9gf4hhdwzuv": {
        "now_playing": "https://www.radiojar.com/api/stations/qt9gf4hhdwzuv/now_playing/",
        "stream": "http://n01.radiojar.com/qt9gf4hhdwzuv?rj-ttl=5&rj-tok=AAABmFLPtM4AjyiEVMC7YOOklQ",
        "name": "Max 93.4"
    },
    "c27wx6pdh8vtv": {
        "now_playing": "https://www.radiojar.com/api/stations/c27wx6pdh8vtv/now_playing/",
        "stream": "https://stream.radiojar.com/c27wx6pdh8vtv",
        "name": "MixFM Cyprus"
    },
    "5tyqrwpgpfeuv": {
        "now_playing": "https://www.radiojar.com/api/stations/5tyqrwpgpfeuv/now_playing/",
        "stream": "http://n13.radiojar.com/5tyqrwpgpfeuv?rj-ttl=5&rj-tok=AAABmFLP8s0AYgulx6iTScVjEg",
        "name": "Monkey Bros Radio"
    },
    "w6c6bssk95vtv": {
        "now_playing": "https://www.radiojar.com/api/stations/w6c6bssk95vtv/now_playing/",
        "stream": "https://stream.radiojar.com/w6c6bssk95vtv",
        "name": "Musica Radio"
    },
    "29e98fkcks3vv": {
        "now_playing": "https://www.radiojar.com/api/stations/29e98fkcks3vv/now_playing/",
        "stream": "http://n05.radiojar.com/29e98fkcks3vv?rj-ttl=5&rj-tok=AAABmFLQL20AmHodLGyqtyDEKA",
        "name": "Nitro 102.5"
    },
    "93c3avwu48hvv": {
        "now_playing": "https://www.radiojar.com/api/stations/93c3avwu48hvv/now_playing/",
        "stream": "http://n10.radiojar.com/93c3avwu48hvv?rj-ttl=5&rj-tok=AAABmFLQXOYApqLYSjLt-OWIiw",
        "name": "NRG 95"
    },
    "apb4wybq36duv": {
        "now_playing": "https://www.radiojar.com/api/stations/apb4wybq36duv/now_playing/",
        "stream": "http://n10.radiojar.com/apb4wybq36duv?rj-ttl=5&rj-tok=AAABmFLQl6cA_-g2vBHUHmssvA",
        "name": "NRG 101.5"
    },
    "u8c2yr3sp42vv": {
        "now_playing": "https://www.radiojar.com/api/stations/u8c2yr3sp42vv/now_playing/",
        "stream": "http://n0f.radiojar.com/u8c2yr3sp42vv?rj-ttl=5&rj-tok=AAABmFLQzdsA6KexJL_YV1cTdQ",
        "name": "Ogdoo"
    },
    "48cz219puzzuv": {
        "now_playing": "https://www.radiojar.com/api/stations/48cz219puzzuv/now_playing/",
        "stream": "http://n0d.radiojar.com/48cz219puzzuv?rj-ttl=5&rj-tok=AAABmFLQ-gUA9-Uv_n1xg2jYFQ",
        "name": "Pemptousia"
    },
    "pepper": {
        "now_playing": "https://www.radiojar.com/api/stations/pepper/now_playing/",
        "stream": "https://stream.radiojar.com/pepper",
        "name": "Pepper 96.6"
    },
    "s87smqqfewzuv": {
        "now_playing": "https://www.radiojar.com/api/stations/s87smqqfewzuv/now_playing/",
        "stream": "http://n0c.radiojar.com/s87smqqfewzuv?rj-ttl=5&rj-tok=AAABmFLROX8A9_MOdzNhICVKzA",
        "name": "Picasso 102.7"
    },
    "431m8b6qcm5tv": {
        "now_playing": "https://www.radiojar.com/api/stations/431m8b6qcm5tv/now_playing/",
        "stream": "https://stream.radiojar.com/431m8b6qcm5tv",
        "name": "Play Gold"
    },
    "gzr6836ty7zuv": {
        "now_playing": "https://www.radiojar.com/api/stations/gzr6836ty7zuv/now_playing/",
        "stream": "http://n01.radiojar.com/gzr6836ty7zuv?rj-ttl=5&rj-tok=AAABmFLRhoQAQSFsXStpY-mIaw",
        "name": "PolisView"
    },
    "weqykpegsm5tv": {
        "now_playing": "https://www.radiojar.com/api/stations/weqykpegsm5tv/now_playing/",
        "stream": "http://n10.radiojar.com/weqykpegsm5tv?rj-ttl=5&rj-tok=AAABmFLRuvAA1L79pr4JF6w2Bg",
        "name": "Purple"
    },
    "kddqnna7yxmtv": {
        "now_playing": "https://www.radiojar.com/api/stations/kddqnna7yxmtv/now_playing/",
        "stream": "http://n02.radiojar.com/kddqnna7yxmtv?rj-ttl=5&rj-tok=AAABmFLR6qAAD5uzE1Zc53fk0A",
        "name": "Radio Paris"
    },
    "yv5xu5h7zwwtv": {
        "now_playing": "https://www.radiojar.com/api/stations/yv5xu5h7zwwtv/now_playing/",
        "stream": "https://stream.radiojar.com/yv5xu5h7zwwtv",
        "name": "Radio X"
    },
    "6uqfysrasm0uv": {
        "now_playing": "https://www.radiojar.com/api/stations/6uqfysrasm0uv/now_playing/",
        "stream": "http://n0c.radiojar.com/6uqfysrasm0uv?rj-ttl=5&rj-tok=AAABmFLSJ3sAV2_R4UQCA3PaFQ",
        "name": "Radiobird"
    },
    "d3n35mr218hvv": {
        "now_playing": "https://www.radiojar.com/api/stations/d3n35mr218hvv/now_playing/",
        "stream": "http://n0c.radiojar.com/d3n35mr218hvv?rj-ttl=5&rj-tok=AAABmFLSW0cAM9B7sbyge_-6jg",
        "name": "RadioMak"
    },
    "gbrgkbcfnq5tv": {
        "now_playing": "https://www.radiojar.com/api/stations/gbrgkbcfnq5tv/now_playing/",
        "stream": "http://n0c.radiojar.com/gbrgkbcfnq5tv?rj-ttl=5&rj-tok=AAABmFLSjpEAwfCBFT9BSkwsbg",
        "name": "Ραδιοτσάμπουνο"
    },
    "radio-apopsi": {
        "now_playing": "https://www.radiojar.com/api/stations/radio-apopsi/now_playing/",
        "stream": "http://n0b.radiojar.com/radio-apopsi?rj-ttl=5&rj-tok=AAABmFLS_I8Asnh4pHOJnNfW_g",
        "name": "Radio Apopsi"
    },
    "083wqknmsuhvv": {
        "now_playing": "https://www.radiojar.com/api/stations/083wqknmsuhvv/now_playing/",
        "stream": "http://n0e.radiojar.com/083wqknmsuhvv?rj-ttl=5&rj-tok=AAABmFLTMrQAyY8Puq-fStp7jQ",
        "name": "Rainbow 89"
    },
    "vhknc3c8ktuvv": {
        "now_playing": "https://www.radiojar.com/api/stations/vhknc3c8ktuvv/now_playing/",
        "stream": "http://n01.radiojar.com/vhknc3c8ktuvv?rj-ttl=5&rj-tok=AAABmFLTszMAjECtkg_BEaX-mw",
        "name": "Rainbow 89 Alternative"
    },
    "ztqh29c8ktuvv": {
        "now_playing": "https://www.radiojar.com/api/stations/ztqh29c8ktuvv/now_playing/",
        "stream": "http://n02.radiojar.com/ztqh29c8ktuvv?rj-ttl=5&rj-tok=AAABmFLT47MARXWl3l1UQdBZWQ",
        "name": "Rainbow 89 Pop"
    },
    "akf7zea5kzuvv": {
        "now_playing": "https://www.radiojar.com/api/stations/akf7zea5kzuvv/now_playing/",
        "stream": "http://n01.radiojar.com/akf7zea5kzuvv?rj-ttl=5&rj-tok=AAABmFLUEhoAwwDVk_GfDfrCIQ",
        "name": "Rainbow 89 Μπλε"
    },
    "4nwwcyesv8hvv": {
        "now_playing": "https://www.radiojar.com/api/stations/4nwwcyesv8hvv/now_playing/",
        "stream": "http://n09.radiojar.com/4nwwcyesv8hvv?rj-ttl=5&rj-tok=AAABmFLUOmgADrZXnjrAHesnQA",
        "name": "Rainbow 89 Christmas"
    },
    "aay95tkmb": {
        "now_playing": "https://www.radiojar.com/api/stations/aay95tkmb/now_playing/",
        "stream": "http://n0f.radiojar.com/aay95tkmb?rj-ttl=5&rj-tok=AAABmFLUbywANhcvcAGKWQvm5A",
        "name": "Roxx Radio "
    },
    "g4tyehk5yvduv": {
        "now_playing": "https://www.radiojar.com/api/stations/g4tyehk5yvduv/now_playing/",
        "stream": "https://stream.radiojar.com/g4tyehk5yvduv",
        "name": "Ρυθμός 94.9"
    },
    "mg2vq26eewzuv": {
        "now_playing": "https://www.radiojar.com/api/stations/mg2vq26eewzuv/now_playing/",
        "stream": "http://n03.radiojar.com/mg2vq26eewzuv?rj-ttl=5&rj-tok=AAABmFLUvK0AB8bvQfWSr--Daw",
        "name": "Sfera 96.6"
    },
    "kzu8u5w8vzuvv": {
        "now_playing": "https://www.radiojar.com/api/stations/kzu8u5w8vzuvv/now_playing/",
        "stream": "http://n0e.radiojar.com/kzu8u5w8vzuvv?rj-ttl=5&rj-tok=AAABmFLU_lAAVQinYlWLcHpvGw",
        "name": "Simple Radio"
    },
    "zeqcyyvu48hvv": {
        "now_playing": "https://www.radiojar.com/api/stations/zeqcyyvu48hvv/now_playing/",
        "stream": "https://stream.radiojar.com/zeqcyyvu48hvv",
        "name": "SokFM 104.8"
    },
    "yb7bcbkfewzuv": {
        "now_playing": "https://www.radiojar.com/api/stations/yb7bcbkfewzuv/now_playing/",
        "stream": "http://n02.radiojar.com/yb7bcbkfewzuv?rj-ttl=5&rj-tok=AAABmFLVTvgA0bEisUACz4BMog",
        "name": "Sport 96.3"
    },
    "fg3tm92rxeruv": {
        "now_playing": "https://www.radiojar.com/api/stations/fg3tm92rxeruv/now_playing/",
        "stream": "https://stream.radiojar.com/fg3tm92rxeruv",
        "name": "Strummer Radio"
    },
    "w47v0ekgzp5tv": {
        "now_playing": "https://www.radiojar.com/api/stations/w47v0ekgzp5tv/now_playing/",
        "stream": "https://stream.radiojar.com/w47v0ekgzp5tv",
        "name": "Weird Fishes"
    },
    "nkqh9th47vzuv": {
        "now_playing": "https://www.radiojar.com/api/stations/nkqh9th47vzuv/now_playing/",
        "stream": "http://n02.radiojar.com/nkqh9th47vzuv?rj-ttl=5&rj-tok=AAABmFLVmIUAXBNkxsCgLNhpXg",
        "name": "Αιγαίο Live 95.8"
    },
    "1qpu1agw4mzuv": {
        "now_playing": "https://www.radiojar.com/api/stations/1qpu1agw4mzuv/now_playing/",
        "stream": "http://n0d.radiojar.com/1qpu1agw4mzuv?rj-ttl=5&rj-tok=AAABmFLVzR4APTT-4wZqobHfPQ",
        "name": "Δημοτικό Ραδιόφωνο Ιωαννίνων 98.7"
    },
    "e8n41erbay8uv": {
        "now_playing": "https://www.radiojar.com/api/stations/e8n41erbay8uv/now_playing/",
        "stream": "http://n0e.radiojar.com/e8n41erbay8uv?rj-ttl=5&rj-tok=AAABmFLV-7AAfLCKLZjy6DFEpQ",
        "name": "ΕΑΠ Non Stop Music"
    },
    "2rsrhmepefq": {
        "now_playing": "https://www.radiojar.com/api/stations/2rsrhmepefq/now_playing/",
        "stream": "http://n07.radiojar.com/2rsrhmepefq?rj-ttl=5&rj-tok=AAABmFLWK10AJxjVMR6atcJ7_w",
        "name": "Έμπνευση 107 FM"
    },
    "g6eg7gpa6k5tv": {
        "now_playing": "https://www.radiojar.com/api/stations/g6eg7gpa6k5tv/now_playing/",
        "stream": "http://n13.radiojar.com/g6eg7gpa6k5tv?rj-ttl=5&rj-tok=AAABmFLWZZYA3gOLsDGpWoLS_g",
        "name": "Μεσόγειος 105.4"
    },
    "f4pqr7wu48hvv": {
        "now_playing": "https://www.radiojar.com/api/stations/f4pqr7wu48hvv/now_playing/",
        "stream": "https://stream.radiojar.com/f4pqr7wu48hvv",
        "name": "Μπλε 99"
    },
    "u34mus9cy72vv": {
        "now_playing": "https://www.radiojar.com/api/stations/u34mus9cy72vv/now_playing/",
        "stream": "http://n11.radiojar.com/u34mus9cy72vv?rj-ttl=5&rj-tok=AAABmFLWqD4AYeI_ZFK6RXoDTA",
        "name": "Παραδοσιακό Radio"
    },
    "un4tp96kb": {
        "now_playing": "https://www.radiojar.com/api/stations/un4tp96kb/now_playing/",
        "stream": "https://stream.radiojar.com/un4tp96kb",
        "name": "Πορτοκαλί"
    },
    "ybz2g5nh5ehvv": {
        "now_playing": "https://www.radiojar.com/api/stations/ybz2g5nh5ehvv/now_playing/",
        "stream": "http://n10.radiojar.com/ybz2g5nh5ehvv?rj-ttl=5&rj-tok=AAABmFLXn_8AEPQETqo7ZBS3iQ",
        "name": "Ράδιο Πάντειον"
    },
    "ypdwy53ce6hvv": {
        "now_playing": "https://www.radiojar.com/api/stations/ypdwy53ce6hvv/now_playing/",
        "stream": "http://n09.radiojar.com/ypdwy53ce6hvv?rj-ttl=5&rj-tok=AAABmFLXyisAGbatWe6YYVZ4Fw",
        "name": "Ράδιο Πάντειον Sports"
    },
    "v1hkvv4gk72vv": {
        "now_playing": "https://www.radiojar.com/api/stations/v1hkvv4gk72vv/now_playing/",
        "stream": "http://n0d.radiojar.com/v1hkvv4gk72vv?rj-ttl=5&rj-tok=AAABmFLX_XwAwOY3loF9kuiNlA",
        "name": "Ρυθμός Κομοτηνής 103.1"
    },
    "819r8wupdrruv": {
        "now_playing": "https://www.radiojar.com/api/stations/819r8wupdrruv/now_playing/",
        "stream": "http://n01.radiojar.com/819r8wupdrruv?rj-ttl=5&rj-tok=AAABmFLYLYoAi-1NY_0JmXnrmw",
        "name": "Σκύλος 90"
    },
    "kokkino-ath": {
        "now_playing": "https://www.radiojar.com/api/stations/kokkino-ath/now_playing/",
        "stream": "https://stream.radiojar.com/kokkino-ath",
        "name": "Στο Κόκκινο 105.5 Αθήνα"
    },
    "275p8ssmb": {
        "now_playing": "https://www.radiojar.com/api/stations/275p8ssmb/now_playing/",
        "stream": "https://stream.radiojar.com/275p8ssmb",
        "name": "Στο Κόκκινο 91,4 Θεσσαλονίκη"
    },
    "s5sa2z0mtceuv": {
        "now_playing": "https://www.radiojar.com/api/stations/s5sa2z0mtceuv/now_playing/",
        "stream": "http://n07.radiojar.com/s5sa2z0mtceuv?rj-ttl=5&rj-tok=AAABmFLYh-YAfbZrwxfeUBxAQg",
        "name": "Στο Κόκκινο Πάτρα 107.7"
    },
    "gnomi": {
        "now_playing": "https://ice.greekstream.net/gnomi.xspf",
        "stream": "https://ice.greekstream.net/gnomi",
        "name": "Γνώμη 93.7"
    },
    "halkidiki988": {
        "now_playing": "https://ice.greekstream.net/988.xspf",
        "stream": "https://ice.greekstream.net/988",
        "name": "Halkidiki 98.8"
    },
    "city1061": {
        "now_playing": "https://ice.greekstream.net/city1061.xspf",
        "stream": "https://ice.greekstream.net/city1061",
        "name": "City 106.1"
    },
    "focusfm": {
        "now_playing": "https://ice.greekstream.net/focusfm.xspf",
        "stream": "https://ice.greekstream.net/focusfm",
        "name": "Focus FM 103.6"
    },
    "praktoreio": {
        "now_playing": "https://ice.greekstream.net/praktoreio.xspf",
        "stream": "https://ice.greekstream.net/praktoreio",
        "name": "Praktoreio 104.9 FM"
    },
    "ekrixifm": {
        "now_playing": "https://ice.greekstream.net/ekrixifm.xspf",
        "stream": "https://ice.greekstream.net/ekrixifm",
        "name": "Radio Ekrixi 99.8"
    },
    "statusfm": {
        "now_playing": "https://ice.greekstream.net/statusfm.xspf",
        "stream": "https://ice.greekstream.net/statusfm",
        "name": "Status FM 107.7"
    },
    "superfm": {
        "now_playing": "https://ice.greekstream.net/superfm.xspf",
        "stream": "https://ice.greekstream.net/superfm",
        "name": "Super FM 101 Thessaloniki"
    },
    "yellow": {
        "now_playing": "https://ice.greekstream.net/yellow.xspf",
        "stream": "https://ice.greekstream.net/yellow",
        "name": "Yellow Radio 101.7"
    },
    "zoo995": {
        "now_playing": "https://ice.greekstream.net/zoo995.xspf",
        "stream": "https://ice.greekstream.net/zoo995",
        "name": "Zoo 90.8"
    }
}
